MANIFEST.in
README.md
setup.py
choice/__init__.py
choice/basicterm.py
choice/util.py
choice.egg-info/PKG-INFO
choice.egg-info/SOURCES.txt
choice.egg-info/dependency_links.txt
choice.egg-info/top_level.txt
test/test.py