Metadata-Version: 1.0
Name: choice
Version: 0.1
Summary: Easy request and response GUI for Python
Home-page: https://github.com/fyhuang/choice
Author: Frank Huang
Author-email: me@nongraphical.com
License: UNKNOWN
Platform: UNKNOWN
Classifier: Programming Language :: Python
Classifier: Programming Language :: Python :: 3
Classifier: License :: OSI Approved :: BSD License
Classifier: Operating System :: OS Independent
Classifier: Development Status :: 3 - Alpha
Classifier: Intended Audience :: Developers
Classifier: Topic :: Software Development :: Libraries :: Python Modules
Classifier: Environment :: Console
